<annotation>
	<folder>Wrench</folder>
	<filename>000377.jpg</filename>
	<path>C:\Users\Narut\Desktop\Proyecto_Ing\tools\Images\Wrench\000377.jpg</path>
	<source>
		<database>Unknown</database>
	</source>
	<size>
		<width>276</width>
		<height>183</height>
		<depth>3</depth>
	</size>
	<segmented>0</segmented>
	<object>
		<name>Socket wrench</name>
		<pose>Unspecified</pose>
		<truncated>1</truncated>
		<difficult>0</difficult>
		<bndbox>
			<xmin>72</xmin>
			<ymin>82</ymin>
			<xmax>120</xmax>
			<ymax>183</ymax>
		</bndbox>
	</object>
	<object>
		<name>Socket wrench</name>
		<pose>Unspecified</pose>
		<truncated>1</truncated>
		<difficult>0</difficult>
		<bndbox>
			<xmin>233</xmin>
			<ymin>73</ymin>
			<xmax>276</xmax>
			<ymax>141</ymax>
		</bndbox>
	</object>
	<object>
		<name>Allen wrench</name>
		<pose>Unspecified</pose>
		<truncated>0</truncated>
		<difficult>0</difficult>
		<bndbox>
			<xmin>145</xmin>
			<ymin>54</ymin>
			<xmax>191</xmax>
			<ymax>75</ymax>
		</bndbox>
	</object>
	<object>
		<name>Combination wrench</name>
		<pose>Unspecified</pose>
		<truncated>0</truncated>
		<difficult>0</difficult>
		<bndbox>
			<xmin>141</xmin>
			<ymin>15</ymin>
			<xmax>153</xmax>
			<ymax>50</ymax>
		</bndbox>
	</object>
	<object>
		<name>Combination wrench</name>
		<pose>Unspecified</pose>
		<truncated>0</truncated>
		<difficult>0</difficult>
		<bndbox>
			<xmin>151</xmin>
			<ymin>15</ymin>
			<xmax>162</xmax>
			<ymax>49</ymax>
		</bndbox>
	</object>
	<object>
		<name>Combination wrench</name>
		<pose>Unspecified</pose>
		<truncated>0</truncated>
		<difficult>0</difficult>
		<bndbox>
			<xmin>161</xmin>
			<ymin>12</ymin>
			<xmax>173</xmax>
			<ymax>49</ymax>
		</bndbox>
	</object>
	<object>
		<name>Combination wrench</name>
		<pose>Unspecified</pose>
		<truncated>0</truncated>
		<difficult>0</difficult>
		<bndbox>
			<xmin>170</xmin>
			<ymin>8</ymin>
			<xmax>184</xmax>
			<ymax>49</ymax>
		</bndbox>
	</object>
	<object>
		<name>Combination wrench</name>
		<pose>Unspecified</pose>
		<truncated>0</truncated>
		<difficult>0</difficult>
		<bndbox>
			<xmin>179</xmin>
			<ymin>7</ymin>
			<xmax>199</xmax>
			<ymax>50</ymax>
		</bndbox>
	</object>
	<object>
		<name>Combination wrench</name>
		<pose>Unspecified</pose>
		<truncated>0</truncated>
		<difficult>0</difficult>
		<bndbox>
			<xmin>190</xmin>
			<ymin>6</ymin>
			<xmax>214</xmax>
			<ymax>49</ymax>
		</bndbox>
	</object>
	<object>
		<name>Combination wrench</name>
		<pose>Unspecified</pose>
		<truncated>0</truncated>
		<difficult>0</difficult>
		<bndbox>
			<xmin>198</xmin>
			<ymin>6</ymin>
			<xmax>224</xmax>
			<ymax>50</ymax>
		</bndbox>
	</object>
	<object>
		<name>Combination wrench</name>
		<pose>Unspecified</pose>
		<truncated>0</truncated>
		<difficult>0</difficult>
		<bndbox>
			<xmin>209</xmin>
			<ymin>4</ymin>
			<xmax>237</xmax>
			<ymax>49</ymax>
		</bndbox>
	</object>
	<object>
		<name>Combination wrench</name>
		<pose>Unspecified</pose>
		<truncated>1</truncated>
		<difficult>0</difficult>
		<bndbox>
			<xmin>219</xmin>
			<ymin>1</ymin>
			<xmax>254</xmax>
			<ymax>47</ymax>
		</bndbox>
	</object>
	<object>
		<name>Combination wrench</name>
		<pose>Unspecified</pose>
		<truncated>1</truncated>
		<difficult>0</difficult>
		<bndbox>
			<xmin>229</xmin>
			<ymin>1</ymin>
			<xmax>266</xmax>
			<ymax>48</ymax>
		</bndbox>
	</object>
	<object>
		<name>Combination wrench</name>
		<pose>Unspecified</pose>
		<truncated>1</truncated>
		<difficult>0</difficult>
		<bndbox>
			<xmin>242</xmin>
			<ymin>1</ymin>
			<xmax>275</xmax>
			<ymax>47</ymax>
		</bndbox>
	</object>
</annotation>
