<annotation>
	<folder>Screwdrivers</folder>
	<filename>000201.jpg</filename>
	<path>C:\Users\Narut\Desktop\Proyecto_Ing\tools\Images\Screwdrivers\000201.jpg</path>
	<source>
		<database>Unknown</database>
	</source>
	<size>
		<width>319</width>
		<height>158</height>
		<depth>3</depth>
	</size>
	<segmented>0</segmented>
	<object>
		<name>Screwdriver</name>
		<pose>Unspecified</pose>
		<truncated>0</truncated>
		<difficult>0</difficult>
		<bndbox>
			<xmin>16</xmin>
			<ymin>46</ymin>
			<xmax>292</xmax>
			<ymax>98</ymax>
		</bndbox>
	</object>
</annotation>
