<annotation>
	<folder>pliers</folder>
	<filename>000316.jpg</filename>
	<path>C:\Users\Narut\Desktop\Proyecto_Ing\tools\Images\pliers\000316.jpg</path>
	<source>
		<database>Unknown</database>
	</source>
	<size>
		<width>275</width>
		<height>183</height>
		<depth>3</depth>
	</size>
	<segmented>0</segmented>
	<object>
		<name>Linesman pliers</name>
		<pose>Unspecified</pose>
		<truncated>0</truncated>
		<difficult>0</difficult>
		<bndbox>
			<xmin>29</xmin>
			<ymin>41</ymin>
			<xmax>232</xmax>
			<ymax>129</ymax>
		</bndbox>
	</object>
</annotation>
